pyGun/__init__.py
pygun-0.0.1a0.dist-info/WHEEL
pygun-0.0.1a0.dist-info/METADATA
pygun-0.0.1a0.dist-info/RECORD
